kadap/__init__.py
kadap/data.py
kadap/benchmarking/__init__.py
kadap/benchmarking/detect.py
kadap/benchmarking/export.py
kadap/benchmarking/data/__init__.py
kadap/benchmarking/data/scripts/__init__.py
kadap/benchmarking/models/__init__.py
kadap/benchmarking/models/common.py
kadap/benchmarking/models/experimental.py
kadap/benchmarking/models/tf.py
kadap/benchmarking/models/yolo.py
kadap/benchmarking/utils/__init__.py
kadap/benchmarking/utils/activations.py
kadap/benchmarking/utils/augmentations.py
kadap/benchmarking/utils/autoanchor.py
kadap/benchmarking/utils/autobatch.py
kadap/benchmarking/utils/callbacks.py
kadap/benchmarking/utils/dataloaders.py
kadap/benchmarking/utils/downloads.py
kadap/benchmarking/utils/general.py
kadap/benchmarking/utils/loss.py
kadap/benchmarking/utils/metrics.py
kadap/benchmarking/utils/plots.py
kadap/benchmarking/utils/torch_utils.py
kadap/benchmarking/utils/triton.py
kadap/benchmarking/utils/aws/__init__.py
kadap/benchmarking/utils/aws/resume.py
kadap/benchmarking/utils/loggers/__init__.py
kadap/benchmarking/utils/loggers/clearml/__init__.py
kadap/benchmarking/utils/loggers/clearml/clearml_utils.py
kadap/benchmarking/utils/loggers/clearml/hpo.py
kadap/benchmarking/utils/loggers/comet/__init__.py
kadap/benchmarking/utils/loggers/comet/comet_utils.py
kadap/benchmarking/utils/loggers/comet/hpo.py
kadap/benchmarking/utils/loggers/wandb/__init__.py
kadap/benchmarking/utils/loggers/wandb/log_dataset.py
kadap/benchmarking/utils/loggers/wandb/sweep.py
kadap/benchmarking/utils/loggers/wandb/wandb_utils.py
kadap/benchmarking/utils/segment/__init__.py
kadap/benchmarking/utils/segment/augmentations.py
kadap/benchmarking/utils/segment/dataloaders.py
kadap/benchmarking/utils/segment/general.py
kadap/benchmarking/utils/segment/loss.py
kadap/benchmarking/utils/segment/metrics.py
kadap/benchmarking/utils/segment/plots.py
kadap/config/__init__.py
kadap/config/config.py
kadap_test-1.0.1.dist-info/LICENSE
kadap_test-1.0.1.dist-info/METADATA
kadap_test-1.0.1.dist-info/WHEEL
kadap_test-1.0.1.dist-info/top_level.txt
kadap_test-1.0.1.dist-info/RECORD
